odoo/addons/shopinvader_price_per_qty/README.rst
odoo/addons/shopinvader_price_per_qty/__init__.py
odoo/addons/shopinvader_price_per_qty/__manifest__.py
odoo/addons/shopinvader_price_per_qty/demo/pricelist_demo.xml
odoo/addons/shopinvader_price_per_qty/i18n/shopinvader_price_per_qty.pot
odoo/addons/shopinvader_price_per_qty/models/__init__.py
odoo/addons/shopinvader_price_per_qty/models/shopinvader_variant.py
odoo/addons/shopinvader_price_per_qty/readme/DESCRIPTION.rst
odoo/addons/shopinvader_price_per_qty/static/description/index.html
odoo/addons/shopinvader_price_per_qty/tests/__init__.py
odoo/addons/shopinvader_price_per_qty/tests/test_product.py
odoo14_addon_shopinvader_price_per_qty-14.0.1.0.1.dist-info/METADATA
odoo14_addon_shopinvader_price_per_qty-14.0.1.0.1.dist-info/WHEEL
odoo14_addon_shopinvader_price_per_qty-14.0.1.0.1.dist-info/top_level.txt
odoo14_addon_shopinvader_price_per_qty-14.0.1.0.1.dist-info/RECORD
